epic_llm/__init__.py
epic_llm/main.py
epic_llm/managers/port.py
epic_llm/managers/provider.py
epic_llm/managers/state.py
epic_llm/providers/__init__.py
epic_llm/providers/base.py
epic_llm/providers/claude.py
epic_llm/providers/copilot.py
epic_llm/providers/gemini.py
epic_llm/utils/__init__.py
epic_llm/utils/auth_middleware.py
epic_llm/utils/auth_validator.py
epic_llm/utils/claude_auth_validator.py
epic_llm/utils/copilot_auth_validator.py
epic_llm/utils/dependencies.py
epic_llm/utils/gateway.py
epic_llm/utils/log_manager.py
epic_llm/utils/log_parsers.py
epic_llm/utils/middleware_daemon.py
epic_llm/utils/paths.py
epic_llm/utils/secure_keys.py
epic_llm/utils/validators.py
epic_llm-0.1.1.dist-info/METADATA
epic_llm-0.1.1.dist-info/WHEEL
epic_llm-0.1.1.dist-info/entry_points.txt
epic_llm-0.1.1.dist-info/licenses/LICENSE
epic_llm-0.1.1.dist-info/RECORD
