Metadata-Version: 2.4
Name: epic-llm
Version: 0.1.1
Summary: Orchestration tool for managing third-party LLM API providers
Project-URL: Homepage, https://github.com/epic-llm/epic-llm
Project-URL: Repository, https://github.com/epic-llm/epic-llm
Project-URL: Issues, https://github.com/epic-llm/epic-llm/issues
Project-URL: Changelog, https://github.com/epic-llm/epic-llm/releases
Author: Dre
License: MIT
License-File: LICENSE
Keywords: api,claude,copilot,gemini,llm,orchestration
Classifier: Development Status :: 4 - Beta
Classifier: Environment :: Console
Classifier: Intended Audience :: Developers
Classifier: License :: OSI Approved :: MIT License
Classifier: Programming Language :: Python :: 3
Classifier: Programming Language :: Python :: 3.10
Classifier: Programming Language :: Python :: 3.11
Classifier: Programming Language :: Python :: 3.12
Classifier: Topic :: Internet :: WWW/HTTP :: HTTP Servers
Classifier: Topic :: Software Development :: Libraries :: Python Modules
Requires-Python: >=3.10
Requires-Dist: aiohttp>=3.8.0
Requires-Dist: bcrypt>=4.0.0
Requires-Dist: httpx>=0.24.0
Requires-Dist: psutil>=5.9.0
Requires-Dist: pydantic>=2.0.0
Requires-Dist: rich>=13.0.0
Requires-Dist: typer>=0.9.0
Provides-Extra: dev
Requires-Dist: mypy>=1.0.0; extra == 'dev'
Requires-Dist: pytest-asyncio>=0.21.0; extra == 'dev'
Requires-Dist: pytest-cov>=4.0.0; extra == 'dev'
Requires-Dist: pytest>=7.0.0; extra == 'dev'
Requires-Dist: ruff>=0.1.0; extra == 'dev'
